AutoDiffGroup23andMe/AutoDiff.py
AutoDiffGroup23andMe/AutoDiffMath.py
AutoDiffGroup23andMe/Optimization.py
AutoDiffGroup23andMe/__init__.py
AutoDiffGroup23andMe-0.0.1.dist-info/METADATA
AutoDiffGroup23andMe-0.0.1.dist-info/WHEEL
AutoDiffGroup23andMe-0.0.1.dist-info/top_level.txt
AutoDiffGroup23andMe-0.0.1.dist-info/RECORD
