Metadata-Version: 2.1
Name: AutoDiffGroup23andMe
Version: 0.0.1
Summary: An optimization tool-kit package utilizing automatic differentiation
Home-page: https://github.com/Group23andMe/cs107-FinalProject
Author: Omead Eftekhari, Drew Pendergrass, Saul Soto, Ryan Liu
Author-email: 
License: UNKNOWN
Platform: UNKNOWN
Classifier: Programming Language :: Python :: 3
Classifier: License :: OSI Approved :: MIT License
Classifier: Operating System :: OS Independent
Requires-Python: >=3.6
